{
  "PreenchaCampos": "Preencha o campo para continuar.",
  "PreenchaCampo": "Preencha o campo {nome} para continuar.",
  "RegistroIncluido": "Registro incluido com sucesso.",
  "RegistroAlterado": "Registro alterado com sucesso.",
  "Removido": "Removido com sucesso.",
  "ErroRemover": "Erro ao remover.",
  "Endereco": "Endereco",
  "TipoPagamento": "Tipo Pagamento",
  "Valor": "Valor",
  "Quantidade": "Quantidade",
  "Nome": "Nome",
  "Descricao": "Descricao",
  "Cidade": "Cidade",
  "Bairro": "Bairro",
  "Email": "Email",
  "Perfil": "Perfil",
  "Senha": "Senha",
  "Categoria": "Categoria",
  "Produto": "Produto",
  "Foto": "Foto",
  "Texto": "Texto",
  "Titulo": "Titulo",
  "Nota": "Nota",
  "Numero": "Numero",
  "Estado": "Estado",
  "Complemento": "Complemento",
  "Referencia": "Referencia",
  "Usuario": "Usuario",
  "Ordem": "Ordem"
}